Workbook

Sheet Модель
A1: КОНТУР / Изменённая
A2: Базовый · KZT · 12 месяцев. Потоки — сумма; остатки — на конец М12.
A3: Чистая прибыль | B3: =N41 -> 9688745.3 | D3: Выручка | E3: =N8 -> 38315804 | G3: Деньги на конец | H3: =M49 -> 10688745
A4: Показатель | B4: М1 | C4: М2 | D4: М3 | E4: М4 | F4: М5 | G4: М6 | H4: М7 | I4: М8 | J4: М9 | K4: М10 | L4: М11 | M4: М12 | N4: Год / конец | O4: Как считается
A5: Основной продукт · количество | B5: =IF(AND((1>='Вводные'!$B$35),(1<='Вводные'!$B$36)),(('Вводные'!$B$31*'Вводные'!$B$17)*((1+('Вводные'!$B$33/100))^MAX(0,(1-'Вводные'!$B$35)))),0) -> 300 | C5: =IF(AND((2>='Вводные'!$B$35),(2<='Вводные'!$B$36)),(('Вводные'!$B$31*'Вводные'!$B$17)*((1+('Вводные'!$B$33/100))^MAX(0,(2-'Вводные'!$B$35)))),0) -> 312 | D5: =IF(AND((3>='Вводные'!$B$35),(3<='Вводные'!$B$36)),(('Вводные'!$B$31*'Вводные'!$B$17)*((1+('Вводные'!$B$33/100))^MAX(0,(3-'Вводные'!$B$35)))),0) -> 324.48 | E5: =IF(AND((4>='Вводные'!$B$35),(4<='Вводные'!$B$36)),(('Вводные'!$B$31*'Вводные'!$B$17)*((1+('Вводные'!$B$33/100))^MAX(0,(4-'Вводные'!$B$35)))),0) -> 337.4592 | F5: =IF(AND((5>='Вводные'!$B$35),(5<='Вводные'!$B$36)),(('Вводные'!$B$31*'Вводные'!$B$17)*((1+('Вводные'!$B$33/100))^MAX(0,(5-'Вводные'!$B$35)))),0) -> 350.95757 | G5: =IF(AND((6>='Вводные'!$B$35),(6<='Вводные'!$B$36)),(('Вводные'!$B$31*'Вводные'!$B$17)*((1+('Вводные'!$B$33/100))^MAX(0,(6-'Вводные'!$B$35)))),0) -> 364.99587 | H5: =IF(AND((7>='Вводные'!$B$35),(7<='Вводные'!$B$36)),(('Вводные'!$B$31*'Вводные'!$B$17)*((1+('Вводные'!$B$33/100))^MAX(0,(7-'Вводные'!$B$35)))),0) -> 379.59571 | I5: =IF(AND((8>='Вводные'!$B$35),(8<='Вводные'!$B$36)),(('Вводные'!$B$31*'Вводные'!$B$17)*((1+('Вводные'!$B$33/100))^MAX(0,(8-'Вводные'!$B$35)))),0) -> 394.77953 | J5: =IF(AND((9>='Вводные'!$B$35),(9<='Вводные'!$B$36)),(('Вводные'!$B$31*'Вводные'!$B$17)*((1+('Вводные'!$B$33/100))^MAX(0,(9-'Вводные'!$B$35)))),0) -> 410.57072 | K5: =IF(AND((10>='Вводные'!$B$35),(10<='Вводные'!$B$36)),(('Вводные'!$B$31*'Вводные'!$B$17)*((1+('Вводные'!$B$33/100))^MAX(0,(10-'Вводные'!$B$35)))),0) -> 426.99354 | L5: =IF(AND((11>='Вводные'!$B$35),(11<='Вводные'!$B$36)),(('Вводные'!$B$31*'Вводные'!$B$17)*((1+('Вводные'!$B$33/100))^MAX(0,(11-'Вводные'!$B$35)))),0) -> 444.07329 | M5: =IF(AND((12>='Вводные'!$B$35),(12<='Вводные'!$B$36)),(('Вводные'!$B$31*'Вводные'!$B$17)*((1+('Вводные'!$B$33/100))^MAX(0,(12-'Вводные'!$B$35)))),0) -> 461.83622 | N5: =SUM(B5:M5) -> 4507.7416 | O5: Продажи
A6: Основной продукт · выручка | B6: =(B5*'Вводные'!$B$32) -> 2550000 | C6: =(C5*'Вводные'!$B$32) -> 2652000 | D6: =(D5*'Вводные'!$B$32) -> 2758080 | E6: =(E5*'Вводные'!$B$32) -> 2868403.2 | F6: =(F5*'Вводные'!$B$32) -> 2983139.3 | G6: =(G5*'Вводные'!$B$32) -> 3102464.9 | H6: =(H5*'Вводные'!$B$32) -> 3226563.5 | I6: =(I5*'Вводные'!$B$32) -> 3355626 | ... M6: =(M5*'Вводные'!$B$32) -> 3925607.8 | N6: =SUM(B6:M6) -> 38315804 | O6: Продажи
A7: Основной продукт · себестоимость | B7: =(B6*('Вводные'!$B$34/100)) -> 892500 | C7: =(C6*('Вводные'!$B$34/100)) -> 928200 | D7: =(D6*('Вводные'!$B$34/100)) -> 965328 | E7: =(E6*('Вводные'!$B$34/100)) -> 1003941.1 | F7: =(F6*('Вводные'!$B$34/100)) -> 1044098.8 | G7: =(G6*('Вводные'!$B$34/100)) -> 1085862.7 | H7: =(H6*('Вводные'!$B$34/100)) -> 1129297.2 | I7: =(I6*('Вводные'!$B$34/100)) -> 1174469.1 | ... M7: =(M6*('Вводные'!$B$34/100)) -> 1373962.7 | N7: =SUM(B7:M7) -> 13410531 | O7: Продажи
A8: Выручка / оборот | B8: =IF(('Вводные'!$B$4="manual"),('Вводные'!$B$18*'Вводные'!$B$17),B6) -> 2550000 | C8: =IF(('Вводные'!$B$4="manual"),('Вводные'!$B$19*'Вводные'!$B$17),C6) -> 2652000 | D8: =IF(('Вводные'!$B$4="manual"),('Вводные'!$B$20*'Вводные'!$B$17),D6) -> 2758080 | E8: =IF(('Вводные'!$B$4="manual"),('Вводные'!$B$21*'Вводные'!$B$17),E6) -> 2868403.2 | F8: =IF(('Вводные'!$B$4="manual"),('Вводные'!$B$22*'Вводные'!$B$17),F6) -> 2983139.3 | G8: =IF(('Вводные'!$B$4="manual"),('Вводные'!$B$23*'Вводные'!$B$17),G6) -> 3102464.9 | H8: =IF(('Вводные'!$B$4="manual"),('Вводные'!$B$24*'Вводные'!$B$17),H6) -> 3226563.5 | I8: =IF(('Вводные'!$B$4="manual"),('Вводные'!$B$25*'Вводные'!$B$17),I6) -> 3355626 | J8: =IF(('Вводные'!$B$4="manual"),('Вводные'!$B$26*'Вводные'!$B$17),J6) -> 3489851.1 | K8: =IF(('Вводные'!$B$4="manual"),('Вводные'!$B$27*'Вводные'!$B$17),K6) -> 3629445.1 | L8: =IF(('Вводные'!$B$4="manual"),('Вводные'!$B$28*'Вводные'!$B$17),L6) -> 3774622.9 | M8: =IF(('Вводные'!$B$4="manual"),('Вводные'!$B$29*'Вводные'!$B$17),M6) -> 3925607.8 | N8: =SUM(B8:M8) -> 38315804 | O8: По продуктам: количество × цена. Вручную: введённый оборот. Сценарий применяется один раз.
A9: Себестоимость продаж | B9: =IF(('Вводные'!$B$4="manual"),(B8*('Вводные'!$B$5/100)),B7) -> 892500 | C9: =IF(('Вводные'!$B$4="manual"),(C8*('Вводные'!$B$5/100)),C7) -> 928200 | D9: =IF(('Вводные'!$B$4="manual"),(D8*('Вводные'!$B$5/100)),D7) -> 965328 | E9: =IF(('Вводные'!$B$4="manual"),(E8*('Вводные'!$B$5/100)),E7) -> 1003941.1 | F9: =IF(('Вводные'!$B$4="manual"),(F8*('Вводные'!$B$5/100)),F7) -> 1044098.8 | G9: =IF(('Вводные'!$B$4="manual"),(G8*('Вводные'!$B$5/100)),G7) -> 1085862.7 | H9: =IF(('Вводные'!$B$4="manual"),(H8*('Вводные'!$B$5/100)),H7) -> 1129297.2 | I9: =IF(('Вводные'!$B$4="manual"),(I8*('Вводные'!$B$5/100)),I7) -> 1174469.1 | ... M9: =IF(('Вводные'!$B$4="manual"),(M8*('Вводные'!$B$5/100)),M7) -> 1373962.7 | N9: =SUM(B9:M9) -> 13410531 | O9: Себестоимость продуктов или доля ручного оборота. Не дублируйте её в прочих расходах.
A10: Валовая прибыль | B10: =(B8-B9) -> 1657500 | C10: =(C8-C9) -> 1723800 | D10: =(D8-D9) -> 1792752 | E10: =(E8-E9) -> 1864462.1 | F10: =(F8-F9) -> 1939040.6 | G10: =(G8-G9) -> 2016602.2 | H10: =(H8-H9) -> 2097266.3 | I10: =(I8-I9) -> 2181156.9 | ... M10: =(M8-M9) -> 2551645.1 | N10: =SUM(B10:M10) -> 24905273 | O10: Выручка − себестоимость.
A11: Менеджер · оклады и бонусы | B11: =IF(AND((1>='Вводные'!$B$43),(1<='Вводные'!$B$44)),(('Вводные'!$B$38*('Вводные'!$B$39+'Вводные'!$B$40))*((1+('Вводные'!$B$42/100))^MAX(0,(1-'Вводные'!$B$43)))),0) -> 300000 | C11: =IF(AND((2>='Вводные'!$B$43),(2<='Вводные'!$B$44)),(('Вводные'!$B$38*('Вводные'!$B$39+'Вводные'!$B$40))*((1+('Вводные'!$B$42/100))^MAX(0,(2-'Вводные'!$B$43)))),0) -> 300000 | D11: =IF(AND((3>='Вводные'!$B$43),(3<='Вводные'!$B$44)),(('Вводные'!$B$38*('Вводные'!$B$39+'Вводные'!$B$40))*((1+('Вводные'!$B$42/100))^MAX(0,(3-'Вводные'!$B$43)))),0) -> 300000 | E11: =IF(AND((4>='Вводные'!$B$43),(4<='Вводные'!$B$44)),(('Вводные'!$B$38*('Вводные'!$B$39+'Вводные'!$B$40))*((1+('Вводные'!$B$42/100))^MAX(0,(4-'Вводные'!$B$43)))),0) -> 300000 | F11: =IF(AND((5>='Вводные'!$B$43),(5<='Вводные'!$B$44)),(('Вводные'!$B$38*('Вводные'!$B$39+'Вводные'!$B$40))*((1+('Вводные'!$B$42/100))^MAX(0,(5-'Вводные'!$B$43)))),0) -> 300000 | G11: =IF(AND((6>='Вводные'!$B$43),(6<='Вводные'!$B$44)),(('Вводные'!$B$38*('Вводные'!$B$39+'Вводные'!$B$40))*((1+('Вводные'!$B$42/100))^MAX(0,(6-'Вводные'!$B$43)))),0) -> 300000 | H11: =IF(AND((7>='Вводные'!$B$43),(7<='Вводные'!$B$44)),(('Вводные'!$B$38*('Вводные'!$B$39+'Вводные'!$B$40))*((1+('Вводные'!$B$42/100))^MAX(0,(7-'Вводные'!$B$43)))),0) -> 300000 | I11: =IF(AND((8>='Вводные'!$B$43),(8<='Вводные'!$B$44)),(('Вводные'!$B$38*('Вводные'!$B$39+'Вводные'!$B$40))*((1+('Вводные'!$B$42/100))^MAX(0,(8-'Вводные'!$B$43)))),0) -> 300000 | J11: =IF(AND((9>='Вводные'!$B$43),(9<='Вводные'!$B$44)),(('Вводные'!$B$38*('Вводные'!$B$39+'Вводные'!$B$40))*((1+('Вводные'!$B$42/100))^MAX(0,(9-'Вводные'!$B$43)))),0) -> 300000 | K11: =IF(AND((10>='Вводные'!$B$43),(10<='Вводные'!$B$44)),(('Вводные'!$B$38*('Вводные'!$B$39+'Вводные'!$B$40))*((1+('Вводные'!$B$42/100))^MAX(0,(10-'Вводные'!$B$43)))),0) -> 300000 | L11: =IF(AND((11>='Вводные'!$B$43),(11<='Вводные'!$B$44)),(('Вводные'!$B$38*('Вводные'!$B$39+'Вводные'!$B$40))*((1+('Вводные'!$B$42/100))^MAX(0,(11-'Вводные'!$B$43)))),0) -> 300000 | M11: =IF(AND((12>='Вводные'!$B$43),(12<='Вводные'!$B$44)),(('Вводные'!$B$38*('Вводные'!$B$39+'Вводные'!$B$40))*((1+('Вводные'!$B$42/100))^MAX(0,(12-'Вводные'!$B$43)))),0) -> 300000 | N11: =SUM(B11:M11) -> 3600000 | O11: Команда
A12: Менеджер · начисления | B12: =(B11*('Вводные'!$B$41/100)) -> 45000 | C12: =(C11*('Вводные'!$B$41/100)) -> 45000 | D12: =(D11*('Вводные'!$B$41/100)) -> 45000 | E12: =(E11*('Вводные'!$B$41/100)) -> 45000 | F12: =(F11*('Вводные'!$B$41/100)) -> 45000 | G12: =(G11*('Вводные'!$B$41/100)) -> 45000 | H12: =(H11*('Вводные'!$B$41/100)) -> 45000 | I12: =(I11*('Вводные'!$B$41/100)) -> 45000 | ... M12: =(M11*('Вводные'!$B$41/100)) -> 45000 | N12: =SUM(B12:M12) -> 540000 | O12: Команда
A13: Менеджер — копия · оклады и бонусы | B13: =IF(AND((1>='Вводные'!$B$51),(1<='Вводные'!$B$52)),(('Вводные'!$B$46*('Вводные'!$B$47+'Вводные'!$B$48))*((1+('Вводные'!$B$50/100))^MAX(0,(1-'Вводные'!$B$51)))),0) -> 300000 | C13: =IF(AND((2>='Вводные'!$B$51),(2<='Вводные'!$B$52)),(('Вводные'!$B$46*('Вводные'!$B$47+'Вводные'!$B$48))*((1+('Вводные'!$B$50/100))^MAX(0,(2-'Вводные'!$B$51)))),0) -> 300000 | D13: =IF(AND((3>='Вводные'!$B$51),(3<='Вводные'!$B$52)),(('Вводные'!$B$46*('Вводные'!$B$47+'Вводные'!$B$48))*((1+('Вводные'!$B$50/100))^MAX(0,(3-'Вводные'!$B$51)))),0) -> 300000 | E13: =IF(AND((4>='Вводные'!$B$51),(4<='Вводные'!$B$52)),(('Вводные'!$B$46*('Вводные'!$B$47+'Вводные'!$B$48))*((1+('Вводные'!$B$50/100))^MAX(0,(4-'Вводные'!$B$51)))),0) -> 300000 | F13: =IF(AND((5>='Вводные'!$B$51),(5<='Вводные'!$B$52)),(('Вводные'!$B$46*('Вводные'!$B$47+'Вводные'!$B$48))*((1+('Вводные'!$B$50/100))^MAX(0,(5-'Вводные'!$B$51)))),0) -> 300000 | G13: =IF(AND((6>='Вводные'!$B$51),(6<='Вводные'!$B$52)),(('Вводные'!$B$46*('Вводные'!$B$47+'Вводные'!$B$48))*((1+('Вводные'!$B$50/100))^MAX(0,(6-'Вводные'!$B$51)))),0) -> 300000 | H13: =IF(AND((7>='Вводные'!$B$51),(7<='Вводные'!$B$52)),(('Вводные'!$B$46*('Вводные'!$B$47+'Вводные'!$B$48))*((1+('Вводные'!$B$50/100))^MAX(0,(7-'Вводные'!$B$51)))),0) -> 300000 | I13: =IF(AND((8>='Вводные'!$B$51),(8<='Вводные'!$B$52)),(('Вводные'!$B$46*('Вводные'!$B$47+'Вводные'!$B$48))*((1+('Вводные'!$B$50/100))^MAX(0,(8-'Вводные'!$B$51)))),0) -> 300000 | J13: =IF(AND((9>='Вводные'!$B$51),(9<='Вводные'!$B$52)),(('Вводные'!$B$46*('Вводные'!$B$47+'Вводные'!$B$48))*((1+('Вводные'!$B$50/100))^MAX(0,(9-'Вводные'!$B$51)))),0) -> 300000 | K13: =IF(AND((10>='Вводные'!$B$51),(10<='Вводные'!$B$52)),(('Вводные'!$B$46*('Вводные'!$B$47+'Вводные'!$B$48))*((1+('Вводные'!$B$50/100))^MAX(0,(10-'Вводные'!$B$51)))),0) -> 300000 | L13: =IF(AND((11>='Вводные'!$B$51),(11<='Вводные'!$B$52)),(('Вводные'!$B$46*('Вводные'!$B$47+'Вводные'!$B$48))*((1+('Вводные'!$B$50/100))^MAX(0,(11-'Вводные'!$B$51)))),0) -> 300000 | M13: =IF(AND((12>='Вводные'!$B$51),(12<='Вводные'!$B$52)),(('Вводные'!$B$46*('Вводные'!$B$47+'Вводные'!$B$48))*((1+('Вводные'!$B$50/100))^MAX(0,(12-'Вводные'!$B$51)))),0) -> 300000 | N13: =SUM(B13:M13) -> 3600000 | O13: Команда
A14: Менеджер — копия · начисления | B14: =(B13*('Вводные'!$B$49/100)) -> 45000 | C14: =(C13*('Вводные'!$B$49/100)) -> 45000 | D14: =(D13*('Вводные'!$B$49/100)) -> 45000 | E14: =(E13*('Вводные'!$B$49/100)) -> 45000 | F14: =(F13*('Вводные'!$B$49/100)) -> 45000 | G14: =(G13*('Вводные'!$B$49/100)) -> 45000 | H14: =(H13*('Вводные'!$B$49/100)) -> 45000 | I14: =(I13*('Вводные'!$B$49/100)) -> 45000 | ... M14: =(M13*('Вводные'!$B$49/100)) -> 45000 | N14: =SUM(B14:M14) -> 540000 | O14: Команда
A15: Оклады и бонусы | B15: =(B11+B13) -> 600000 | C15: =(C11+C13) -> 600000 | D15: =(D11+D13) -> 600000 | E15: =(E11+E13) -> 600000 | F15: =(F11+F13) -> 600000 | G15: =(G11+G13) -> 600000 | H15: =(H11+H13) -> 600000 | I15: =(I11+I13) -> 600000 | ... M15: =(M11+M13) -> 600000 | N15: =SUM(B15:M15) -> 7200000 | O15: Команда
A16: Начисления работодателя | B16: =(B12+B14) -> 90000 | C16: =(C12+C14) -> 90000 | D16: =(D12+D14) -> 90000 | E16: =(E12+E14) -> 90000 | F16: =(F12+F14) -> 90000 | G16: =(G12+G14) -> 90000 | H16: =(H12+H14) -> 90000 | I16: =(I12+I14) -> 90000 | ... M16: =(M12+M14) -> 90000 | N16: =SUM(B16:M16) -> 1080000 | O16: Команда
A17: Команда — всего | B17: =(B15+B16) -> 690000 | C17: =(C15+C16) -> 690000 | D17: =(D15+D16) -> 690000 | E17: =(E15+E16) -> 690000 | F17: =(F15+F16) -> 690000 | G17: =(G15+G16) -> 690000 | H17: =(H15+H16) -> 690000 | I17: =(I15+I16) -> 690000 | ... M17: =(M15+M16) -> 690000 | N17: =SUM(B17:M17) -> 8280000 | O17: Количество × (оклад + бонус) × рост × (1 + начисления). Ставки задаёте вы.
A18: Реклама · затраты | B18: =IF(AND((1>='Вводные'!$B$61),(1<='Вводные'!$B$62)),(('Вводные'!$B$54*((1+('Вводные'!$B$56/100))^MAX(0,(1-'Вводные'!$B$61))))+(B8*('Вводные'!$B$55/100))),0) -> 120000 | C18: =IF(AND((2>='Вводные'!$B$61),(2<='Вводные'!$B$62)),(('Вводные'!$B$54*((1+('Вводные'!$B$56/100))^MAX(0,(2-'Вводные'!$B$61))))+(C8*('Вводные'!$B$55/100))),0) -> 120000 | D18: =IF(AND((3>='Вводные'!$B$61),(3<='Вводные'!$B$62)),(('Вводные'!$B$54*((1+('Вводные'!$B$56/100))^MAX(0,(3-'Вводные'!$B$61))))+(D8*('Вводные'!$B$55/100))),0) -> 120000 | E18: =IF(AND((4>='Вводные'!$B$61),(4<='Вводные'!$B$62)),(('Вводные'!$B$54*((1+('Вводные'!$B$56/100))^MAX(0,(4-'Вводные'!$B$61))))+(E8*('Вводные'!$B$55/100))),0) -> 120000 | F18: =IF(AND((5>='Вводные'!$B$61),(5<='Вводные'!$B$62)),(('Вводные'!$B$54*((1+('Вводные'!$B$56/100))^MAX(0,(5-'Вводные'!$B$61))))+(F8*('Вводные'!$B$55/100))),0) -> 120000 | G18: =IF(AND((6>='Вводные'!$B$61),(6<='Вводные'!$B$62)),(('Вводные'!$B$54*((1+('Вводные'!$B$56/100))^MAX(0,(6-'Вводные'!$B$61))))+(G8*('Вводные'!$B$55/100))),0) -> 120000 | H18: =IF(AND((7>='Вводные'!$B$61),(7<='Вводные'!$B$62)),(('Вводные'!$B$54*((1+('Вводные'!$B$56/100))^MAX(0,(7-'Вводные'!$B$61))))+(H8*('Вводные'!$B$55/100))),0) -> 120000 | I18: =IF(AND((8>='Вводные'!$B$61),(8<='Вводные'!$B$62)),(('Вводные'!$B$54*((1+('Вводные'!$B$56/100))^MAX(0,(8-'Вводные'!$B$61))))+(I8*('Вводные'!$B$55/100))),0) -> 120000 | J18: =IF(AND((9>='Вводные'!$B$61),(9<='Вводные'!$B$62)),(('Вводные'!$B$54*((1+('Вводные'!$B$56/100))^MAX(0,(9-'Вводные'!$B$61))))+(J8*('Вводные'!$B$55/100))),0) -> 120000 | K18: =IF(AND((10>='Вводные'!$B$61),(10<='Вводные'!$B$62)),(('Вводные'!$B$54*((1+('Вводные'!$B$56/100))^MAX(0,(10-'Вводные'!$B$61))))+(K8*('Вводные'!$B$55/100))),0) -> 120000 | L18: =IF(AND((11>='Вводные'!$B$61),(11<='Вводные'!$B$62)),(('Вводные'!$B$54*((1+('Вводные'!$B$56/100))^MAX(0,(11-'Вводные'!$B$61))))+(L8*('Вводные'!$B$55/100))),0) -> 120000 | M18: =IF(AND((12>='Вводные'!$B$61),(12<='Вводные'!$B$62)),(('Вводные'!$B$54*((1+('Вводные'!$B$56/100))^MAX(0,(12-'Вводные'!$B$61))))+(M8*('Вводные'!$B$55/100))),0) -> 120000 | N18: =SUM(B18:M18) -> 1440000 | O18: Маркетинг
A19: Реклама · клики | B19: =IF(('Вводные'!$B$57>0),(B18/'Вводные'!$B$57),0) -> 800 | C19: =IF(('Вводные'!$B$57>0),(C18/'Вводные'!$B$57),0) -> 800 | D19: =IF(('Вводные'!$B$57>0),(D18/'Вводные'!$B$57),0) -> 800 | E19: =IF(('Вводные'!$B$57>0),(E18/'Вводные'!$B$57),0) -> 800 | F19: =IF(('Вводные'!$B$57>0),(F18/'Вводные'!$B$57),0) -> 800 | G19: =IF(('Вводные'!$B$57>0),(G18/'Вводные'!$B$57),0) -> 800 | H19: =IF(('Вводные'!$B$57>0),(H18/'Вводные'!$B$57),0) -> 800 | I19: =IF(('Вводные'!$B$57>0),(I18/'Вводные'!$B$57),0) -> 800 | ... M19: =IF(('Вводные'!$B$57>0),(M18/'Вводные'!$B$57),0) -> 800 | N19: =SUM(B19:M19) -> 9600 | O19: Маркетинг
A20: Реклама · заявки | B20: =(B19*('Вводные'!$B$58/100)) -> 80 | C20: =(C19*('Вводные'!$B$58/100)) -> 80 | D20: =(D19*('Вводные'!$B$58/100)) -> 80 | E20: =(E19*('Вводные'!$B$58/100)) -> 80 | F20: =(F19*('Вводные'!$B$58/100)) -> 80 | G20: =(G19*('Вводные'!$B$58/100)) -> 80 | H20: =(H19*('Вводные'!$B$58/100)) -> 80 | I20: =(I19*('Вводные'!$B$58/100)) -> 80 | ... M20: =(M19*('Вводные'!$B$58/100)) -> 80 | N20: =SUM(B20:M20) -> 960 | O20: Маркетинг
A21: Реклама · клиенты | B21: =(B20*('Вводные'!$B$59/100)) -> 16 | C21: =(C20*('Вводные'!$B$59/100)) -> 16 | D21: =(D20*('Вводные'!$B$59/100)) -> 16 | E21: =(E20*('Вводные'!$B$59/100)) -> 16 | F21: =(F20*('Вводные'!$B$59/100)) -> 16 | G21: =(G20*('Вводные'!$B$59/100)) -> 16 | H21: =(H20*('Вводные'!$B$59/100)) -> 16 | I21: =(I20*('Вводные'!$B$59/100)) -> 16 | ... M21: =(M20*('Вводные'!$B$59/100)) -> 16 | N21: =SUM(B21:M21) -> 192 | O21: Маркетинг
A22: Реклама · оценка выручки | B22: =(B21*'Вводные'!$B$60) -> 136000 | C22: =(C21*'Вводные'!$B$60) -> 136000 | D22: =(D21*'Вводные'!$B$60) -> 136000 | E22: =(E21*'Вводные'!$B$60) -> 136000 | F22: =(F21*'Вводные'!$B$60) -> 136000 | G22: =(G21*'Вводные'!$B$60) -> 136000 | H22: =(H21*'Вводные'!$B$60) -> 136000 | I22: =(I21*'Вводные'!$B$60) -> 136000 | ... M22: =(M21*'Вводные'!$B$60) -> 136000 | N22: =SUM(B22:M22) -> 1632000 | O22: Маркетинг
A23: Маркетинг — всего | B23: =B18 -> 120000 | C23: =C18 -> 120000 | D23: =D18 -> 120000 | E23: =E18 -> 120000 | F23: =F18 -> 120000 | G23: =G18 -> 120000 | H23: =H18 -> 120000 | I23: =I18 -> 120000 | ... M23: =M18 -> 120000 | N23: =SUM(B23:M23) -> 1440000 | O23: Бюджеты каналов + процент от выручки. Продажи из воронки уже должны входить в общий оборот.
A24: Заявки из рекламы, шт. | B24: =B20 -> 80 | C24: =C20 -> 80 | D24: =D20 -> 80 | E24: =E20 -> 80 | F24: =F20 -> 80 | G24: =G20 -> 80 | H24: =H20 -> 80 | I24: =I20 -> 80 | ... M24: =M20 -> 80 | N24: =SUM(B24:M24) -> 960 | O24: Маркетинг
A25: Клиенты из рекламы, шт. | B25: =B21 -> 16 | C25: =C21 -> 16 | D25: =D21 -> 16 | E25: =E21 -> 16 | F25: =F21 -> 16 | G25: =G21 -> 16 | H25: =H21 -> 16 | I25: =I21 -> 16 | ... M25: =M21 -> 16 | N25: =SUM(B25:M25) -> 192 | O25: Маркетинг
A26: Оценка выручки из рекламы | B26: =B22 -> 136000 | C26: =C22 -> 136000 | D26: =D22 -> 136000 | E26: =E22 -> 136000 | F26: =F22 -> 136000 | G26: =G22 -> 136000 | H26: =H22 -> 136000 | I26: =I22 -> 136000 | ... M26: =M22 -> 136000 | N26: =SUM(B26:M26) -> 1632000 | O26: Клиенты × чек каждого канала. Не прибавляется к обороту, чтобы не считать продажи дважды.
A27: Аренда | B27: =IF(AND(AND((1>='Вводные'!$B$67),(1<='Вводные'!$B$68)),IF(('Вводные'!$B$64="once"),(1='Вводные'!$B$67),TRUE)),IF(('Вводные'!$B$64="percent"),(B8*('Вводные'!$B$65/100)),('Вводные'!$B$65*((1+('Вводные'!$B$66/100))^MAX(0,(1-'Вводные'!$B$67))))),0) -> 250000 | C27: =IF(AND(AND((2>='Вводные'!$B$67),(2<='Вводные'!$B$68)),IF(('Вводные'!$B$64="once"),(2='Вводные'!$B$67),TRUE)),IF(('Вводные'!$B$64="percent"),(C8*('Вводные'!$B$65/100)),('Вводные'!$B$65*((1+('Вводные'!$B$66/100))^MAX(0,(2-'Вводные'!$B$67))))),0) -> 250000 | D27: =IF(AND(AND((3>='Вводные'!$B$67),(3<='Вводные'!$B$68)),IF(('Вводные'!$B$64="once"),(3='Вводные'!$B$67),TRUE)),IF(('Вводные'!$B$64="percent"),(D8*('Вводные'!$B$65/100)),('Вводные'!$B$65*((1+('Вводные'!$B$66/100))^MAX(0,(3-'Вводные'!$B$67))))),0) -> 250000 | E27: =IF(AND(AND((4>='Вводные'!$B$67),(4<='Вводные'!$B$68)),IF(('Вводные'!$B$64="once"),(4='Вводные'!$B$67),TRUE)),IF(('Вводные'!$B$64="percent"),(E8*('Вводные'!$B$65/100)),('Вводные'!$B$65*((1+('Вводные'!$B$66/100))^MAX(0,(4-'Вводные'!$B$67))))),0) -> 250000 | F27: =IF(AND(AND((5>='Вводные'!$B$67),(5<='Вводные'!$B$68)),IF(('Вводные'!$B$64="once"),(5='Вводные'!$B$67),TRUE)),IF(('Вводные'!$B$64="percent"),(F8*('Вводные'!$B$65/100)),('Вводные'!$B$65*((1+('Вводные'!$B$66/100))^MAX(0,(5-'Вводные'!$B$67))))),0) -> 250000 | G27: =IF(AND(AND((6>='Вводные'!$B$67),(6<='Вводные'!$B$68)),IF(('Вводные'!$B$64="once"),(6='Вводные'!$B$67),TRUE)),IF(('Вводные'!$B$64="percent"),(G8*('Вводные'!$B$65/100)),('Вводные'!$B$65*((1+('Вводные'!$B$66/100))^MAX(0,(6-'Вводные'!$B$67))))),0) -> 250000 | H27: =IF(AND(AND((7>='Вводные'!$B$67),(7<='Вводные'!$B$68)),IF(('Вводные'!$B$64="once"),(7='Вводные'!$B$67),TRUE)),IF(('Вводные'!$B$64="percent"),(H8*('Вводные'!$B$65/100)),('Вводные'!$B$65*((1+('Вводные'!$B$66/100))^MAX(0,(7-'Вводные'!$B$67))))),0) -> 250000 | I27: =IF(AND(AND((8>='Вводные'!$B$67),(8<='Вводные'!$B$68)),IF(('Вводные'!$B$64="once"),(8='Вводные'!$B$67),TRUE)),IF(('Вводные'!$B$64="percent"),(I8*('Вводные'!$B$65/100)),('Вводные'!$B$65*((1+('Вводные'!$B$66/100))^MAX(0,(8-'Вводные'!$B$67))))),0) -> 250000 | J27: =IF(AND(AND((9>='Вводные'!$B$67),(9<='Вводные'!$B$68)),IF(('Вводные'!$B$64="once"),(9='Вводные'!$B$67),TRUE)),IF(('Вводные'!$B$64="percent"),(J8*('Вводные'!$B$65/100)),('Вводные'!$B$65*((1+('Вводные'!$B$66/100))^MAX(0,(9-'Вводные'!$B$67))))),0) -> 250000 | K27: =IF(AND(AND((10>='Вводные'!$B$67),(10<='Вводные'!$B$68)),IF(('Вводные'!$B$64="once"),(10='Вводные'!$B$67),TRUE)),IF(('Вводные'!$B$64="percent"),(K8*('Вводные'!$B$65/100)),('Вводные'!$B$65*((1+('Вводные'!$B$66/100))^MAX(0,(10-'Вводные'!$B$67))))),0) -> 250000 | L27: =IF(AND(AND((11>='Вводные'!$B$67),(11<='Вводные'!$B$68)),IF(('Вводные'!$B$64="once"),(11='Вводные'!$B$67),TRUE)),IF(('Вводные'!$B$64="percent"),(L8*('Вводные'!$B$65/100)),('Вводные'!$B$65*((1+('Вводные'!$B$66/100))^MAX(0,(11-'Вводные'!$B$67))))),0) -> 250000 | M27: =IF(AND(AND((12>='Вводные'!$B$67),(12<='Вводные'!$B$68)),IF(('Вводные'!$B$64="once"),(12='Вводные'!$B$67),TRUE)),IF(('Вводные'!$B$64="percent"),(M8*('Вводные'!$B$65/100)),('Вводные'!$B$65*((1+('Вводные'!$B$66/100))^MAX(0,(12-'Вводные'!$B$67))))),0) -> 250000 | N27: =SUM(B27:M27) -> 3000000 | O27: Прочие расходы
A28: Сервисы и связь | B28: =IF(AND(AND((1>='Вводные'!$B$73),(1<='Вводные'!$B$74)),IF(('Вводные'!$B$70="once"),(1='Вводные'!$B$73),TRUE)),IF(('Вводные'!$B$70="percent"),(B8*('Вводные'!$B$71/100)),('Вводные'!$B$71*((1+('Вводные'!$B$72/100))^MAX(0,(1-'Вводные'!$B$73))))),0) -> 35000 | C28: =IF(AND(AND((2>='Вводные'!$B$73),(2<='Вводные'!$B$74)),IF(('Вводные'!$B$70="once"),(2='Вводные'!$B$73),TRUE)),IF(('Вводные'!$B$70="percent"),(C8*('Вводные'!$B$71/100)),('Вводные'!$B$71*((1+('Вводные'!$B$72/100))^MAX(0,(2-'Вводные'!$B$73))))),0) -> 35000 | D28: =IF(AND(AND((3>='Вводные'!$B$73),(3<='Вводные'!$B$74)),IF(('Вводные'!$B$70="once"),(3='Вводные'!$B$73),TRUE)),IF(('Вводные'!$B$70="percent"),(D8*('Вводные'!$B$71/100)),('Вводные'!$B$71*((1+('Вводные'!$B$72/100))^MAX(0,(3-'Вводные'!$B$73))))),0) -> 35000 | E28: =IF(AND(AND((4>='Вводные'!$B$73),(4<='Вводные'!$B$74)),IF(('Вводные'!$B$70="once"),(4='Вводные'!$B$73),TRUE)),IF(('Вводные'!$B$70="percent"),(E8*('Вводные'!$B$71/100)),('Вводные'!$B$71*((1+('Вводные'!$B$72/100))^MAX(0,(4-'Вводные'!$B$73))))),0) -> 35000 | F28: =IF(AND(AND((5>='Вводные'!$B$73),(5<='Вводные'!$B$74)),IF(('Вводные'!$B$70="once"),(5='Вводные'!$B$73),TRUE)),IF(('Вводные'!$B$70="percent"),(F8*('Вводные'!$B$71/100)),('Вводные'!$B$71*((1+('Вводные'!$B$72/100))^MAX(0,(5-'Вводные'!$B$73))))),0) -> 35000 | G28: =IF(AND(AND((6>='Вводные'!$B$73),(6<='Вводные'!$B$74)),IF(('Вводные'!$B$70="once"),(6='Вводные'!$B$73),TRUE)),IF(('Вводные'!$B$70="percent"),(G8*('Вводные'!$B$71/100)),('Вводные'!$B$71*((1+('Вводные'!$B$72/100))^MAX(0,(6-'Вводные'!$B$73))))),0) -> 35000 | H28: =IF(AND(AND((7>='Вводные'!$B$73),(7<='Вводные'!$B$74)),IF(('Вводные'!$B$70="once"),(7='Вводные'!$B$73),TRUE)),IF(('Вводные'!$B$70="percent"),(H8*('Вводные'!$B$71/100)),('Вводные'!$B$71*((1+('Вводные'!$B$72/100))^MAX(0,(7-'Вводные'!$B$73))))),0) -> 35000 | I28: =IF(AND(AND((8>='Вводные'!$B$73),(8<='Вводные'!$B$74)),IF(('Вводные'!$B$70="once"),(8='Вводные'!$B$73),TRUE)),IF(('Вводные'!$B$70="percent"),(I8*('Вводные'!$B$71/100)),('Вводные'!$B$71*((1+('Вводные'!$B$72/100))^MAX(0,(8-'Вводные'!$B$73))))),0) -> 35000 | J28: =IF(AND(AND((9>='Вводные'!$B$73),(9<='Вводные'!$B$74)),IF(('Вводные'!$B$70="once"),(9='Вводные'!$B$73),TRUE)),IF(('Вводные'!$B$70="percent"),(J8*('Вводные'!$B$71/100)),('Вводные'!$B$71*((1+('Вводные'!$B$72/100))^MAX(0,(9-'Вводные'!$B$73))))),0) -> 35000 | K28: =IF(AND(AND((10>='Вводные'!$B$73),(10<='Вводные'!$B$74)),IF(('Вводные'!$B$70="once"),(10='Вводные'!$B$73),TRUE)),IF(('Вводные'!$B$70="percent"),(K8*('Вводные'!$B$71/100)),('Вводные'!$B$71*((1+('Вводные'!$B$72/100))^MAX(0,(10-'Вводные'!$B$73))))),0) -> 35000 | L28: =IF(AND(AND((11>='Вводные'!$B$73),(11<='Вводные'!$B$74)),IF(('Вводные'!$B$70="once"),(11='Вводные'!$B$73),TRUE)),IF(('Вводные'!$B$70="percent"),(L8*('Вводные'!$B$71/100)),('Вводные'!$B$71*((1+('Вводные'!$B$72/100))^MAX(0,(11-'Вводные'!$B$73))))),0) -> 35000 | M28: =IF(AND(AND((12>='Вводные'!$B$73),(12<='Вводные'!$B$74)),IF(('Вводные'!$B$70="once"),(12='Вводные'!$B$73),TRUE)),IF(('Вводные'!$B$70="percent"),(M8*('Вводные'!$B$71/100)),('Вводные'!$B$71*((1+('Вводные'!$B$72/100))^MAX(0,(12-'Вводные'!$B$73))))),0) -> 35000 | N28: =SUM(B28:M28) -> 420000 | O28: Прочие расходы
A29: Прочие расходы — всего | B29: =(B27+B28) -> 285000 | C29: =(C27+C28) -> 285000 | D29: =(D27+D28) -> 285000 | E29: =(E27+E28) -> 285000 | F29: =(F27+F28) -> 285000 | G29: =(G27+G28) -> 285000 | H29: =(H27+H28) -> 285000 | I29: =(I27+I28) -> 285000 | ... M29: =(M27+M28) -> 285000 | N29: =SUM(B29:M29) -> 3420000 | O29: Результат
A30: Операционные расходы | B30: =((B17+B23)+B29) -> 1095000 | C30: =((C17+C23)+C29) -> 1095000 | D30: =((D17+D23)+D29) -> 1095000 | E30: =((E17+E23)+E29) -> 1095000 | F30: =((F17+F23)+F29) -> 1095000 | G30: =((G17+G23)+G29) -> 1095000 | H30: =((H17+H23)+H29) -> 1095000 | I30: =((I17+I23)+I29) -> 1095000 | ... M30: =((M17+M23)+M29) -> 1095000 | N30: =SUM(B30:M30) -> 13140000 | O30: Команда + маркетинг + прочие расходы.
A31: EBITDA | B31: =(B10-B30) -> 562500 | C31: =(C10-C30) -> 628800 | D31: =(D10-D30) -> 697752 | E31: =(E10-E30) -> 769462.08 | F31: =(F10-F30) -> 844040.56 | G31: =(G10-G30) -> 921602.19 | H31: =(H10-H30) -> 1002266.3 | I31: =(I10-I30) -> 1086156.9 | ... M31: =(M10-M30) -> 1456645.1 | N31: =SUM(B31:M31) -> 11765273 | O31: Валовая прибыль − операционные расходы; до амортизации, процентов и налога.
A32: Покупка активов | B32: =0 -> 0 | C32: =0 -> 0 | D32: =0 -> 0 | E32: =0 -> 0 | F32: =0 -> 0 | G32: =0 -> 0 | H32: =0 -> 0 | I32: =0 -> 0 | ... M32: =0 -> 0 | N32: =SUM(B32:M32) -> 0 | O32: Денежный поток
A33: Амортизация | B33: =(IF(AND(('Вводные'!$B$13>0),(1<='Вводные'!$B$13)),('Вводные'!$B$12/MAX(1,'Вводные'!$B$13)),0)+0) -> 83333.333 | C33: =(IF(AND(('Вводные'!$B$13>0),(2<='Вводные'!$B$13)),('Вводные'!$B$12/MAX(1,'Вводные'!$B$13)),0)+0) -> 83333.333 | D33: =(IF(AND(('Вводные'!$B$13>0),(3<='Вводные'!$B$13)),('Вводные'!$B$12/MAX(1,'Вводные'!$B$13)),0)+0) -> 83333.333 | E33: =(IF(AND(('Вводные'!$B$13>0),(4<='Вводные'!$B$13)),('Вводные'!$B$12/MAX(1,'Вводные'!$B$13)),0)+0) -> 83333.333 | F33: =(IF(AND(('Вводные'!$B$13>0),(5<='Вводные'!$B$13)),('Вводные'!$B$12/MAX(1,'Вводные'!$B$13)),0)+0) -> 83333.333 | G33: =(IF(AND(('Вводные'!$B$13>0),(6<='Вводные'!$B$13)),('Вводные'!$B$12/MAX(1,'Вводные'!$B$13)),0)+0) -> 83333.333 | H33: =(IF(AND(('Вводные'!$B$13>0),(7<='Вводные'!$B$13)),('Вводные'!$B$12/MAX(1,'Вводные'!$B$13)),0)+0) -> 83333.333 | I33: =(IF(AND(('Вводные'!$B$13>0),(8<='Вводные'!$B$13)),('Вводные'!$B$12/MAX(1,'Вводные'!$B$13)),0)+0) -> 83333.333 | J33: =(IF(AND(('Вводные'!$B$13>0),(9<='Вводные'!$B$13)),('Вводные'!$B$12/MAX(1,'Вводные'!$B$13)),0)+0) -> 83333.333 | K33: =(IF(AND(('Вводные'!$B$13>0),(10<='Вводные'!$B$13)),('Вводные'!$B$12/MAX(1,'Вводные'!$B$13)),0)+0) -> 83333.333 | L33: =(IF(AND(('Вводные'!$B$13>0),(11<='Вводные'!$B$13)),('Вводные'!$B$12/MAX(1,'Вводные'!$B$13)),0)+0) -> 83333.333 | M33: =(IF(AND(('Вводные'!$B$13>0),(12<='Вводные'!$B$13)),('Вводные'!$B$12/MAX(1,'Вводные'!$B$13)),0)+0) -> 83333.333 | N33: =SUM(B33:M33) -> 1000000 | O33: Стоимость / срок в месяцах, начиная с месяца покупки. Покупка уменьшает деньги, амортизация — прибыль.
A34: Операционная прибыль (EBIT) | B34: =(B31-B33) -> 479166.67 | C34: =(C31-C33) -> 545466.67 | D34: =(D31-D33) -> 614418.67 | E34: =(E31-E33) -> 686128.75 | F34: =(F31-F33) -> 760707.23 | G34: =(G31-G33) -> 838268.85 | H34: =(H31-H33) -> 918932.94 | I34: =(I31-I33) -> 1002823.6 | ... M34: =(M31-M33) -> 1373311.8 | N34: =SUM(B34:M34) -> 10765273 | O34: Результат
A35: Кредит на начало месяца | B35: =IF((1<='Вводные'!$B$16),MAX(0,IF(((('Вводные'!$B$15/100)/12)>0),(('Вводные'!$B$14*((1+(('Вводные'!$B$15/100)/12))^0))-(IF(((('Вводные'!$B$15/100)/12)>0),(('Вводные'!$B$14*(('Вводные'!$B$15/100)/12))/(1-((1+(('Вводные'!$B$15/100)/12))^(-1*'Вводные'!$B$16)))),('Вводные'!$B$14/'Вводные'!$B$16))*((((1+(('Вводные'!$B$15/100)/12))^0)-1)/(('Вводные'!$B$15/100)/12)))),('Вводные'!$B$14-(IF(((('Вводные'!$B$15/100)/12)>0),(('Вводные'!$B$14*(('Вводные'!$B$15/100)/12))/(1-((1+(('Вводные'!$B$15/100)/12))^(-1*'Вводные'!$B$16)))),('Вводные'!$B$14/'Вводные'!$B$16))*0)))),0) -> 0 | C35: =IF((2<='Вводные'!$B$16),MAX(0,IF(((('Вводные'!$B$15/100)/12)>0),(('Вводные'!$B$14*((1+(('Вводные'!$B$15/100)/12))^1))-(IF(((('Вводные'!$B$15/100)/12)>0),(('Вводные'!$B$14*(('Вводные'!$B$15/100)/12))/(1-((1+(('Вводные'!$B$15/100)/12))^(-1*'Вводные'!$B$16)))),('Вводные'!$B$14/'Вводные'!$B$16))*((((1+(('Вводные'!$B$15/100)/12))^1)-1)/(('Вводные'!$B$15/100)/12)))),('Вводные'!$B$14-(IF(((('Вводные'!$B$15/100)/12)>0),(('Вводные'!$B$14*(('Вводные'!$B$15/100)/12))/(1-((1+(('Вводные'!$B$15/100)/12))^(-1*'Вводные'!$B$16)))),('Вводные'!$B$14/'Вводные'!$B$16))*1)))),0) -> 0 | D35: =IF((3<='Вводные'!$B$16),MAX(0,IF(((('Вводные'!$B$15/100)/12)>0),(('Вводные'!$B$14*((1+(('Вводные'!$B$15/100)/12))^2))-(IF(((('Вводные'!$B$15/100)/12)>0),(('Вводные'!$B$14*(('Вводные'!$B$15/100)/12))/(1-((1+(('Вводные'!$B$15/100)/12))^(-1*'Вводные'!$B$16)))),('Вводные'!$B$14/'Вводные'!$B$16))*((((1+(('Вводные'!$B$15/100)/12))^2)-1)/(('Вводные'!$B$15/100)/12)))),('Вводные'!$B$14-(IF(((('Вводные'!$B$15/100)/12)>0),(('Вводные'!$B$14*(('Вводные'!$B$15/100)/12))/(1-((1+(('Вводные'!$B$15/100)/12))^(-1*'Вводные'!$B$16)))),('Вводные'!$B$14/'Вводные'!$B$16))*2)))),0) -> 0 | E35: =IF((4<='Вводные'!$B$16),MAX(0,IF(((('Вводные'!$B$15/100)/12)>0),(('Вводные'!$B$14*((1+(('Вводные'!$B$15/100)/12))^3))-(IF(((('Вводные'!$B$15/100)/12)>0),(('Вводные'!$B$14*(('Вводные'!$B$15/100)/12))/(1-((1+(('Вводные'!$B$15/100)/12))^(-1*'Вводные'!$B$16)))),('Вводные'!$B$14/'Вводные'!$B$16))*((((1+(('Вводные'!$B$15/100)/12))^3)-1)/(('Вводные'!$B$15/100)/12)))),('Вводные'!$B$14-(IF(((('Вводные'!$B$15/100)/12)>0),(('Вводные'!$B$14*(('Вводные'!$B$15/100)/12))/(1-((1+(('Вводные'!$B$15/100)/12))^(-1*'Вводные'!$B$16)))),('Вводные'!$B$14/'Вводные'!$B$16))*3)))),0) -> 0 | F35: =IF((5<='Вводные'!$B$16),MAX(0,IF(((('Вводные'!$B$15/100)/12)>0),(('Вводные'!$B$14*((1+(('Вводные'!$B$15/100)/12))^4))-(IF(((('Вводные'!$B$15/100)/12)>0),(('Вводные'!$B$14*(('Вводные'!$B$15/100)/12))/(1-((1+(('Вводные'!$B$15/100)/12))^(-1*'Вводные'!$B$16)))),('Вводные'!$B$14/'Вводные'!$B$16))*((((1+(('Вводные'!$B$15/100)/12))^4)-1)/(('Вводные'!$B$15/100)/12)))),('Вводные'!$B$14-(IF(((('Вводные'!$B$15/100)/12)>0),(('Вводные'!$B$14*(('Вводные'!$B$15/100)/12))/(1-((1+(('Вводные'!$B$15/100)/12))^(-1*'Вводные'!$B$16)))),('Вводные'!$B$14/'Вводные'!$B$16))*4)))),0) -> 0 | G35: =IF((6<='Вводные'!$B$16),MAX(0,IF(((('Вводные'!$B$15/100)/12)>0),(('Вводные'!$B$14*((1+(('Вводные'!$B$15/100)/12))^5))-(IF(((('Вводные'!$B$15/100)/12)>0),(('Вводные'!$B$14*(('Вводные'!$B$15/100)/12))/(1-((1+(('Вводные'!$B$15/100)/12))^(-1*'Вводные'!$B$16)))),('Вводные'!$B$14/'Вводные'!$B$16))*((((1+(('Вводные'!$B$15/100)/12))^5)-1)/(('Вводные'!$B$15/100)/12)))),('Вводные'!$B$14-(IF(((('Вводные'!$B$15/100)/12)>0),(('Вводные'!$B$14*(('Вводные'!$B$15/100)/12))/(1-((1+(('Вводные'!$B$15/100)/12))^(-1*'Вводные'!$B$16)))),('Вводные'!$B$14/'Вводные'!$B$16))*5)))),0) -> 0 | H35: =IF((7<='Вводные'!$B$16),MAX(0,IF(((('Вводные'!$B$15/100)/12)>0),(('Вводные'!$B$14*((1+(('Вводные'!$B$15/100)/12))^6))-(IF(((('Вводные'!$B$15/100)/12)>0),(('Вводные'!$B$14*(('Вводные'!$B$15/100)/12))/(1-((1+(('Вводные'!$B$15/100)/12))^(-1*'Вводные'!$B$16)))),('Вводные'!$B$14/'Вводные'!$B$16))*((((1+(('Вводные'!$B$15/100)/12))^6)-1)/(('Вводные'!$B$15/100)/12)))),('Вводные'!$B$14-(IF(((('Вводные'!$B$15/100)/12)>0),(('Вводные'!$B$14*(('Вводные'!$B$15/100)/12))/(1-((1+(('Вводные'!$B$15/100)/12))^(-1*'Вводные'!$B$16)))),('Вводные'!$B$14/'Вводные'!$B$16))*6)))),0) -> 0 | I35: =IF((8<='Вводные'!$B$16),MAX(0,IF(((('Вводные'!$B$15/100)/12)>0),(('Вводные'!$B$14*((1+(('Вводные'!$B$15/100)/12))^7))-(IF(((('Вводные'!$B$15/100)/12)>0),(('Вводные'!$B$14*(('Вводные'!$B$15/100)/12))/(1-((1+(('Вводные'!$B$15/100)/12))^(-1*'Вводные'!$B$16)))),('Вводные'!$B$14/'Вводные'!$B$16))*((((1+(('Вводные'!$B$15/100)/12))^7)-1)/(('Вводные'!$B$15/100)/12)))),('Вводные'!$B$14-(IF(((('Вводные'!$B$15/100)/12)>0),(('Вводные'!$B$14*(('Вводные'!$B$15/100)/12))/(1-((1+(('Вводные'!$B$15/100)/12))^(-1*'Вводные'!$B$16)))),('Вводные'!$B$14/'Вводные'!$B$16))*7)))),0) -> 0 | J35: =IF((9<='Вводные'!$B$16),MAX(0,IF(((('Вводные'!$B$15/100)/12)>0),(('Вводные'!$B$14*((1+(('Вводные'!$B$15/100)/12))^8))-(IF(((('Вводные'!$B$15/100)/12)>0),(('Вводные'!$B$14*(('Вводные'!$B$15/100)/12))/(1-((1+(('Вводные'!$B$15/100)/12))^(-1*'Вводные'!$B$16)))),('Вводные'!$B$14/'Вводные'!$B$16))*((((1+(('Вводные'!$B$15/100)/12))^8)-1)/(('Вводные'!$B$15/100)/12)))),('Вводные'!$B$14-(IF(((('Вводные'!$B$15/100)/12)>0),(('Вводные'!$B$14*(('Вводные'!$B$15/100)/12))/(1-((1+(('Вводные'!$B$15/100)/12))^(-1*'Вводные'!$B$16)))),('Вводные'!$B$14/'Вводные'!$B$16))*8)))),0) -> 0 | K35: =IF((10<='Вводные'!$B$16),MAX(0,IF(((('Вводные'!$B$15/100)/12)>0),(('Вводные'!$B$14*((1+(('Вводные'!$B$15/100)/12))^9))-(IF(((('Вводные'!$B$15/100)/12)>0),(('Вводные'!$B$14*(('Вводные'!$B$15/100)/12))/(1-((1+(('Вводные'!$B$15/100)/12))^(-1*'Вводные'!$B$16)))),('Вводные'!$B$14/'Вводные'!$B$16))*((((1+(('Вводные'!$B$15/100)/12))^9)-1)/(('Вводные'!$B$15/100)/12)))),('Вводные'!$B$14-(IF(((('Вводные'!$B$15/100)/12)>0),(('Вводные'!$B$14*(('Вводные'!$B$15/100)/12))/(1-((1+(('Вводные'!$B$15/100)/12))^(-1*'Вводные'!$B$16)))),('Вводные'!$B$14/'Вводные'!$B$16))*9)))),0) -> 0 | L35: =IF((11<='Вводные'!$B$16),MAX(0,IF(((('Вводные'!$B$15/100)/12)>0),(('Вводные'!$B$14*((1+(('Вводные'!$B$15/100)/12))^10))-(IF(((('Вводные'!$B$15/100)/12)>0),(('Вводные'!$B$14*(('Вводные'!$B$15/100)/12))/(1-((1+(('Вводные'!$B$15/100)/12))^(-1*'Вводные'!$B$16)))),('Вводные'!$B$14/'Вводные'!$B$16))*((((1+(('Вводные'!$B$15/100)/12))^10)-1)/(('Вводные'!$B$15/100)/12)))),('Вводные'!$B$14-(IF(((('Вводные'!$B$15/100)/12)>0),(('Вводные'!$B$14*(('Вводные'!$B$15/100)/12))/(1-((1+(('Вводные'!$B$15/100)/12))^(-1*'Вводные'!$B$16)))),('Вводные'!$B$14/'Вводные'!$B$16))*10)))),0) -> 0 | M35: =IF((12<='Вводные'!$B$16),MAX(0,IF(((('Вводные'!$B$15/100)/12)>0),(('Вводные'!$B$14*((1+(('Вводные'!$B$15/100)/12))^11))-(IF(((('Вводные'!$B$15/100)/12)>0),(('Вводные'!$B$14*(('Вводные'!$B$15/100)/12))/(1-((1+(('Вводные'!$B$15/100)/12))^(-1*'Вводные'!$B$16)))),('Вводные'!$B$14/'Вводные'!$B$16))*((((1+(('Вводные'!$B$15/100)/12))^11)-1)/(('Вводные'!$B$15/100)/12)))),('Вводные'!$B$14-(IF(((('Вводные'!$B$15/100)/12)>0),(('Вводные'!$B$14*(('Вводные'!$B$15/100)/12))/(1-((1+(('Вводные'!$B$15/100)/12))^(-1*'Вводные'!$B$16)))),('Вводные'!$B$14/'Вводные'!$B$16))*11)))),0) -> 0 | N35: =M35 -> 0 | O35: Кредит
A36: Проценты по кредиту | B36: =(B35*(('Вводные'!$B$15/100)/12)) -> 0 | C36: =(C35*(('Вводные'!$B$15/100)/12)) -> 0 | D36: =(D35*(('Вводные'!$B$15/100)/12)) -> 0 | E36: =(E35*(('Вводные'!$B$15/100)/12)) -> 0 | F36: =(F35*(('Вводные'!$B$15/100)/12)) -> 0 | G36: =(G35*(('Вводные'!$B$15/100)/12)) -> 0 | H36: =(H35*(('Вводные'!$B$15/100)/12)) -> 0 | I36: =(I35*(('Вводные'!$B$15/100)/12)) -> 0 | ... M36: =(M35*(('Вводные'!$B$15/100)/12)) -> 0 | N36: =SUM(B36:M36) -> 0 | O36: Результат
A37: Погашение тела кредита | B37: =IF((1<='Вводные'!$B$16),MIN(B35,MAX(0,(IF(((('Вводные'!$B$15/100)/12)>0),(('Вводные'!$B$14*(('Вводные'!$B$15/100)/12))/(1-((1+(('Вводные'!$B$15/100)/12))^(-1*'Вводные'!$B$16)))),('Вводные'!$B$14/'Вводные'!$B$16))-B36))),0) -> 0 | C37: =IF((2<='Вводные'!$B$16),MIN(C35,MAX(0,(IF(((('Вводные'!$B$15/100)/12)>0),(('Вводные'!$B$14*(('Вводные'!$B$15/100)/12))/(1-((1+(('Вводные'!$B$15/100)/12))^(-1*'Вводные'!$B$16)))),('Вводные'!$B$14/'Вводные'!$B$16))-C36))),0) -> 0 | D37: =IF((3<='Вводные'!$B$16),MIN(D35,MAX(0,(IF(((('Вводные'!$B$15/100)/12)>0),(('Вводные'!$B$14*(('Вводные'!$B$15/100)/12))/(1-((1+(('Вводные'!$B$15/100)/12))^(-1*'Вводные'!$B$16)))),('Вводные'!$B$14/'Вводные'!$B$16))-D36))),0) -> 0 | E37: =IF((4<='Вводные'!$B$16),MIN(E35,MAX(0,(IF(((('Вводные'!$B$15/100)/12)>0),(('Вводные'!$B$14*(('Вводные'!$B$15/100)/12))/(1-((1+(('Вводные'!$B$15/100)/12))^(-1*'Вводные'!$B$16)))),('Вводные'!$B$14/'Вводные'!$B$16))-E36))),0) -> 0 | F37: =IF((5<='Вводные'!$B$16),MIN(F35,MAX(0,(IF(((('Вводные'!$B$15/100)/12)>0),(('Вводные'!$B$14*(('Вводные'!$B$15/100)/12))/(1-((1+(('Вводные'!$B$15/100)/12))^(-1*'Вводные'!$B$16)))),('Вводные'!$B$14/'Вводные'!$B$16))-F36))),0) -> 0 | G37: =IF((6<='Вводные'!$B$16),MIN(G35,MAX(0,(IF(((('Вводные'!$B$15/100)/12)>0),(('Вводные'!$B$14*(('Вводные'!$B$15/100)/12))/(1-((1+(('Вводные'!$B$15/100)/12))^(-1*'Вводные'!$B$16)))),('Вводные'!$B$14/'Вводные'!$B$16))-G36))),0) -> 0 | H37: =IF((7<='Вводные'!$B$16),MIN(H35,MAX(0,(IF(((('Вводные'!$B$15/100)/12)>0),(('Вводные'!$B$14*(('Вводные'!$B$15/100)/12))/(1-((1+(('Вводные'!$B$15/100)/12))^(-1*'Вводные'!$B$16)))),('Вводные'!$B$14/'Вводные'!$B$16))-H36))),0) -> 0 | I37: =IF((8<='Вводные'!$B$16),MIN(I35,MAX(0,(IF(((('Вводные'!$B$15/100)/12)>0),(('Вводные'!$B$14*(('Вводные'!$B$15/100)/12))/(1-((1+(('Вводные'!$B$15/100)/12))^(-1*'Вводные'!$B$16)))),('Вводные'!$B$14/'Вводные'!$B$16))-I36))),0) -> 0 | J37: =IF((9<='Вводные'!$B$16),MIN(J35,MAX(0,(IF(((('Вводные'!$B$15/100)/12)>0),(('Вводные'!$B$14*(('Вводные'!$B$15/100)/12))/(1-((1+(('Вводные'!$B$15/100)/12))^(-1*'Вводные'!$B$16)))),('Вводные'!$B$14/'Вводные'!$B$16))-J36))),0) -> 0 | K37: =IF((10<='Вводные'!$B$16),MIN(K35,MAX(0,(IF(((('Вводные'!$B$15/100)/12)>0),(('Вводные'!$B$14*(('Вводные'!$B$15/100)/12))/(1-((1+(('Вводные'!$B$15/100)/12))^(-1*'Вводные'!$B$16)))),('Вводные'!$B$14/'Вводные'!$B$16))-K36))),0) -> 0 | L37: =IF((11<='Вводные'!$B$16),MIN(L35,MAX(0,(IF(((('Вводные'!$B$15/100)/12)>0),(('Вводные'!$B$14*(('Вводные'!$B$15/100)/12))/(1-((1+(('Вводные'!$B$15/100)/12))^(-1*'Вводные'!$B$16)))),('Вводные'!$B$14/'Вводные'!$B$16))-L36))),0) -> 0 | M37: =IF((12<='Вводные'!$B$16),MIN(M35,MAX(0,(IF(((('Вводные'!$B$15/100)/12)>0),(('Вводные'!$B$14*(('Вводные'!$B$15/100)/12))/(1-((1+(('Вводные'!$B$15/100)/12))^(-1*'Вводные'!$B$16)))),('Вводные'!$B$14/'Вводные'!$B$16))-M36))),0) -> 0 | N37: =SUM(B37:M37) -> 0 | O37: Аннуитетный платёж − проценты. Тело кредита уменьшает деньги, но не прибыль.
A38: Кредит на конец месяца | B38: =MAX(0,(B35-B37)) -> 0 | C38: =MAX(0,(C35-C37)) -> 0 | D38: =MAX(0,(D35-D37)) -> 0 | E38: =MAX(0,(E35-E37)) -> 0 | F38: =MAX(0,(F35-F37)) -> 0 | G38: =MAX(0,(G35-G37)) -> 0 | H38: =MAX(0,(H35-H37)) -> 0 | I38: =MAX(0,(I35-I37)) -> 0 | ... M38: =MAX(0,(M35-M37)) -> 0 | N38: =M38 -> 0 | O38: Кредит
A39: Прибыль до налога | B39: =(B34-B36) -> 479166.67 | C39: =(C34-C36) -> 545466.67 | D39: =(D34-D36) -> 614418.67 | E39: =(E34-E36) -> 686128.75 | F39: =(F34-F36) -> 760707.23 | G39: =(G34-G36) -> 838268.85 | H39: =(H34-H36) -> 918932.94 | I39: =(I34-I36) -> 1002823.6 | ... M39: =(M34-M36) -> 1373311.8 | N39: =SUM(B39:M39) -> 10765273 | O39: Результат
A40: Условный налог | B40: =IF(('Вводные'!$B$6="none"),0,(IF(('Вводные'!$B$6="revenue"),B8,MAX(0,B39))*('Вводные'!$B$7/100))) -> 47916.667 | C40: =IF(('Вводные'!$B$6="none"),0,(IF(('Вводные'!$B$6="revenue"),C8,MAX(0,C39))*('Вводные'!$B$7/100))) -> 54546.667 | D40: =IF(('Вводные'!$B$6="none"),0,(IF(('Вводные'!$B$6="revenue"),D8,MAX(0,D39))*('Вводные'!$B$7/100))) -> 61441.867 | E40: =IF(('Вводные'!$B$6="none"),0,(IF(('Вводные'!$B$6="revenue"),E8,MAX(0,E39))*('Вводные'!$B$7/100))) -> 68612.875 | F40: =IF(('Вводные'!$B$6="none"),0,(IF(('Вводные'!$B$6="revenue"),F8,MAX(0,F39))*('Вводные'!$B$7/100))) -> 76070.723 | G40: =IF(('Вводные'!$B$6="none"),0,(IF(('Вводные'!$B$6="revenue"),G8,MAX(0,G39))*('Вводные'!$B$7/100))) -> 83826.885 | H40: =IF(('Вводные'!$B$6="none"),0,(IF(('Вводные'!$B$6="revenue"),H8,MAX(0,H39))*('Вводные'!$B$7/100))) -> 91893.294 | I40: =IF(('Вводные'!$B$6="none"),0,(IF(('Вводные'!$B$6="revenue"),I8,MAX(0,I39))*('Вводные'!$B$7/100))) -> 100282.36 | ... M40: =IF(('Вводные'!$B$6="none"),0,(IF(('Вводные'!$B$6="revenue"),M8,MAX(0,M39))*('Вводные'!$B$7/100))) -> 137331.18 | N40: =SUM(B40:M40) -> 1076527.3 | O40: Ваша ставка × оборот или положительная прибыль месяца. Без переноса убытков. Оплата в том же месяце.
A41: Чистая прибыль | B41: =(B39-B40) -> 431250 | C41: =(C39-C40) -> 490920 | D41: =(D39-D40) -> 552976.8 | E41: =(E39-E40) -> 617515.87 | F41: =(F39-F40) -> 684636.51 | G41: =(G39-G40) -> 754441.97 | H41: =(H39-H40) -> 827039.65 | I41: =(I39-I40) -> 902541.23 | ... M41: =(M39-M40) -> 1235980.6 | N41: =SUM(B41:M41) -> 9688745.3 | O41: Выручка − себестоимость − команда − маркетинг − прочие − амортизация − проценты − налог.
A42: Все расходы в прибыли | B42: =(B8-B41) -> 2118750 | C42: =(C8-C41) -> 2161080 | D42: =(D8-D41) -> 2205103.2 | E42: =(E8-E41) -> 2250887.3 | F42: =(F8-F41) -> 2298502.8 | G42: =(G8-G41) -> 2348022.9 | H42: =(H8-H41) -> 2399523.9 | I42: =(I8-I41) -> 2453084.8 | ... M42: =(M8-M41) -> 2689627.3 | N42: =SUM(B42:M42) -> 28627059 | O42: Результат
A43: Оплата от клиентов | B43: =IF(1-'Вводные'!$B$8>0,INDEX($B$8:$M$8,1,MAX(1,1-'Вводные'!$B$8)),0) -> 2550000 | C43: =IF(2-'Вводные'!$B$8>0,INDEX($B$8:$M$8,1,MAX(1,2-'Вводные'!$B$8)),0) -> 2652000 | D43: =IF(3-'Вводные'!$B$8>0,INDEX($B$8:$M$8,1,MAX(1,3-'Вводные'!$B$8)),0) -> 2758080 | E43: =IF(4-'Вводные'!$B$8>0,INDEX($B$8:$M$8,1,MAX(1,4-'Вводные'!$B$8)),0) -> 2868403.2 | F43: =IF(5-'Вводные'!$B$8>0,INDEX($B$8:$M$8,1,MAX(1,5-'Вводные'!$B$8)),0) -> 2983139.3 | G43: =IF(6-'Вводные'!$B$8>0,INDEX($B$8:$M$8,1,MAX(1,6-'Вводные'!$B$8)),0) -> 3102464.9 | H43: =IF(7-'Вводные'!$B$8>0,INDEX($B$8:$M$8,1,MAX(1,7-'Вводные'!$B$8)),0) -> 3226563.5 | I43: =IF(8-'Вводные'!$B$8>0,INDEX($B$8:$M$8,1,MAX(1,8-'Вводные'!$B$8)),0) -> 3355626 | J43: =IF(9-'Вводные'!$B$8>0,INDEX($B$8:$M$8,1,MAX(1,9-'Вводные'!$B$8)),0) -> 3489851.1 | K43: =IF(10-'Вводные'!$B$8>0,INDEX($B$8:$M$8,1,MAX(1,10-'Вводные'!$B$8)),0) -> 3629445.1 | L43: =IF(11-'Вводные'!$B$8>0,INDEX($B$8:$M$8,1,MAX(1,11-'Вводные'!$B$8)),0) -> 3774622.9 | M43: =IF(12-'Вводные'!$B$8>0,INDEX($B$8:$M$8,1,MAX(1,12-'Вводные'!$B$8)),0) -> 3925607.8 | N43: =SUM(B43:M43) -> 38315804 | O43: Денежный поток
A44: Оплата себестоимости | B44: =IF(1-'Вводные'!$B$9>0,INDEX($B$9:$M$9,1,MAX(1,1-'Вводные'!$B$9)),0) -> 892500 | C44: =IF(2-'Вводные'!$B$9>0,INDEX($B$9:$M$9,1,MAX(1,2-'Вводные'!$B$9)),0) -> 928200 | D44: =IF(3-'Вводные'!$B$9>0,INDEX($B$9:$M$9,1,MAX(1,3-'Вводные'!$B$9)),0) -> 965328 | E44: =IF(4-'Вводные'!$B$9>0,INDEX($B$9:$M$9,1,MAX(1,4-'Вводные'!$B$9)),0) -> 1003941.1 | F44: =IF(5-'Вводные'!$B$9>0,INDEX($B$9:$M$9,1,MAX(1,5-'Вводные'!$B$9)),0) -> 1044098.8 | G44: =IF(6-'Вводные'!$B$9>0,INDEX($B$9:$M$9,1,MAX(1,6-'Вводные'!$B$9)),0) -> 1085862.7 | H44: =IF(7-'Вводные'!$B$9>0,INDEX($B$9:$M$9,1,MAX(1,7-'Вводные'!$B$9)),0) -> 1129297.2 | I44: =IF(8-'Вводные'!$B$9>0,INDEX($B$9:$M$9,1,MAX(1,8-'Вводные'!$B$9)),0) -> 1174469.1 | J44: =IF(9-'Вводные'!$B$9>0,INDEX($B$9:$M$9,1,MAX(1,9-'Вводные'!$B$9)),0) -> 1221447.9 | K44: =IF(10-'Вводные'!$B$9>0,INDEX($B$9:$M$9,1,MAX(1,10-'Вводные'!$B$9)),0) -> 1270305.8 | L44: =IF(11-'Вводные'!$B$9>0,INDEX($B$9:$M$9,1,MAX(1,11-'Вводные'!$B$9)),0) -> 1321118 | M44: =IF(12-'Вводные'!$B$9>0,INDEX($B$9:$M$9,1,MAX(1,12-'Вводные'!$B$9)),0) -> 1373962.7 | N44: =SUM(B44:M44) -> 13410531 | O44: Денежный поток
A45: Дебиторская задолженность | B45: =(0+(B8-B43)) -> 0 | C45: =(B45+(C8-C43)) -> 0 | D45: =(C45+(D8-D43)) -> 0 | E45: =(D45+(E8-E43)) -> 0 | F45: =(E45+(F8-F43)) -> 0 | G45: =(F45+(G8-G43)) -> 0 | H45: =(G45+(H8-H43)) -> 0 | I45: =(H45+(I8-I43)) -> 0 | J45: =(I45+(J8-J43)) -> 0 | ... M45: =(L45+(M8-M43)) -> 0 | N45: =M45 -> 0 | O45: Оборотный капитал
A46: Кредиторская задолженность | B46: =(0+(B9-B44)) -> 0 | C46: =(B46+(C9-C44)) -> 0 | D46: =(C46+(D9-D44)) -> 0 | E46: =(D46+(E9-E44)) -> 0 | F46: =(E46+(F9-F44)) -> 0 | G46: =(F46+(G9-G44)) -> 0 | H46: =(G46+(H9-H44)) -> 0 | I46: =(H46+(I9-I44)) -> 0 | J46: =(I46+(J9-J44)) -> 0 | ... M46: =(L46+(M9-M44)) -> 0 | N46: =M46 -> 0 | O46: Оборотный капитал
A47: Операционный денежный поток | B47: =((B43-B44)-((B30+B36)+B40)) -> 514583.33 | C47: =((C43-C44)-((C30+C36)+C40)) -> 574253.33 | D47: =((D43-D44)-((D30+D36)+D40)) -> 636310.13 | E47: =((E43-E44)-((E30+E36)+E40)) -> 700849.21 | F47: =((F43-F44)-((F30+F36)+F40)) -> 767969.84 | G47: =((G43-G44)-((G30+G36)+G40)) -> 837775.3 | H47: =((H43-H44)-((H30+H36)+H40)) -> 910372.98 | I47: =((I43-I44)-((I30+I36)+I40)) -> 985874.57 | ... M47: =((M43-M44)-((M30+M36)+M40)) -> 1319313.9 | N47: =SUM(B47:M47) -> 10688745 | O47: Оплата клиентов − оплаченная себестоимость − операционные расходы − проценты − налог. Без амортизации.
A48: Изменение денег за месяц | B48: =((B47-B32)-B37) -> 514583.33 | C48: =((C47-C32)-C37) -> 574253.33 | D48: =((D47-D32)-D37) -> 636310.13 | E48: =((E47-E32)-E37) -> 700849.21 | F48: =((F47-F32)-F37) -> 767969.84 | G48: =((G47-G32)-G37) -> 837775.3 | H48: =((H47-H32)-H37) -> 910372.98 | I48: =((I47-I32)-I37) -> 985874.57 | ... M48: =((M47-M32)-M37) -> 1319313.9 | N48: =SUM(B48:M48) -> 10688745 | O48: Операционный поток − покупка активов − тело кредита.
A49: Деньги на конец месяца | B49: =(((('Вводные'!$B$10+'Вводные'!$B$11)+'Вводные'!$B$14)-'Вводные'!$B$12)+B48) -> 514583.33 | C49: =(B49+C48) -> 1088836.7 | D49: =(C49+D48) -> 1725146.8 | E49: =(D49+E48) -> 2425996 | F49: =(E49+F48) -> 3193965.8 | G49: =(F49+G48) -> 4031741.1 | H49: =(G49+H48) -> 4942114.1 | I49: =(H49+I48) -> 5927988.7 | J49: =(I49+J48) -> 6992384.9 | ... M49: =(L49+M48) -> 10688745 | N49: =M49 -> 10688745 | O49: Старт = деньги на начало + взнос собственника + кредит − начальные вложения. Затем прибавляется изменение денег.
A50: Покрытие вложений, накопленно | B50: =((-1*'Вводные'!$B$12)+(B47-B32)) -> -2485416.7 | C50: =(B50+(C47-C32)) -> -1911163.3 | D50: =(C50+(D47-D32)) -> -1274853.2 | E50: =(D50+(E47-E32)) -> -574003.99 | F50: =(E50+(F47-F32)) -> 193965.85 | G50: =(F50+(G47-G32)) -> 1031741.1 | H50: =(G50+(H47-H32)) -> 1942114.1 | I50: =(H50+(I47-I32)) -> 2927988.7 | J50: =(I50+(J47-J32)) -> 3992384.9 | ... M50: =(L50+(M47-M32)) -> 7688745.3 | N50: =M50 -> 7688745.3 | O50: Накопленный операционный поток − вложения. Без взносов, выдачи и тела кредита; после процентов. Поздние покупки могут снова уменьшить показатель.
A51: Маржа чистой прибыли | B51: =IF(B8>0,B41/B8,"") -> 0.16911765 | C51: =IF(C8>0,C41/C8,"") -> 0.18511312 | D51: =IF(D8>0,D41/D8,"") -> 0.20049339 | E51: =IF(E8>0,E41/E8,"") -> 0.2152821 | F51: =IF(F8>0,F41/F8,"") -> 0.22950202 | G51: =IF(G8>0,G41/G8,"") -> 0.24317502 | H51: =IF(H8>0,H41/H8,"") -> 0.25632214 | I51: =IF(I8>0,I41/I8,"") -> 0.26896359 | ... N51: =IF(N8>0,N41/N8,"") -> 0.25286551
A52: CAC: стоимость клиента | B52: =IF(B25>0,B23/B25,"") -> 7500 | C52: =IF(C25>0,C23/C25,"") -> 7500 | D52: =IF(D25>0,D23/D25,"") -> 7500 | E52: =IF(E25>0,E23/E25,"") -> 7500 | F52: =IF(F25>0,F23/F25,"") -> 7500 | G52: =IF(G25>0,G23/G25,"") -> 7500 | H52: =IF(H25>0,H23/H25,"") -> 7500 | I52: =IF(I25>0,I23/I25,"") -> 7500 | ... N52: =IF(N25>0,N23/N25,"") -> 7500
A53: CPL: стоимость заявки | B53: =IF(B24>0,B23/B24,"") -> 1500 | C53: =IF(C24>0,C23/C24,"") -> 1500 | D53: =IF(D24>0,D23/D24,"") -> 1500 | E53: =IF(E24>0,E23/E24,"") -> 1500 | F53: =IF(F24>0,F23/F24,"") -> 1500 | G53: =IF(G24>0,G23/G24,"") -> 1500 | H53: =IF(H24>0,H23/H24,"") -> 1500 | I53: =IF(I24>0,I23/I24,"") -> 1500 | ... N53: =IF(N24>0,N23/N24,"") -> 1500
A54: ROAS: рекламная выручка / бюджет | B54: =IF(B23>0,B26/B23,"") -> 1.1333333 | C54: =IF(C23>0,C26/C23,"") -> 1.1333333 | D54: =IF(D23>0,D26/D23,"") -> 1.1333333 | E54: =IF(E23>0,E26/E23,"") -> 1.1333333 | F54: =IF(F23>0,F26/F23,"") -> 1.1333333 | G54: =IF(G23>0,G26/G23,"") -> 1.1333333 | H54: =IF(H23>0,H26/H23,"") -> 1.1333333 | I54: =IF(I23>0,I26/I23,"") -> 1.1333333 | ... N54: =IF(N23>0,N26/N23,"") -> 1.1333333
A55: Стартовый остаток | N55: =('Вводные'!B10+'Вводные'!B11+'Вводные'!B14-'Вводные'!B12) -> 0
A56: Дополнительное финансирование | N56: =MAX(0,-MIN(('Вводные'!B10+'Вводные'!B11+'Вводные'!B14-'Вводные'!B12),B49:M49)) -> 0 | O56: По минимуму остатка на старте и концах месяцев; внутримесячные разрывы не оцениваются.
A57: Безубыточная выручка М1 | N57: =IF((1-IF('Вводные'!B4="manual",'Вводные'!B5/100,IF(B8>0,B9/B8,1))-(IF(AND('Вводные'!B64="percent",'Вводные'!B67=1),'Вводные'!B65/100,0)+IF(AND('Вводные'!B70="percent",'Вводные'!B73=1),'Вводные'!B71/100,0)+IF('Вводные'!B61=1,'Вводные'!B55/100,0)+0)-IF('Вводные'!B6="revenue",'Вводные'!B7/100,0))>0,(B30-B8*(IF(AND('Вводные'!B64="percent",'Вводные'!B67=1),'Вводные'!B65/100,0)+IF(AND('Вводные'!B70="percent",'Вводные'!B73=1),'Вводные'!B71/100,0)+IF('Вводные'!B61=1,'Вводные'!B55/100,0)+0)+B33+B36)/(1-IF('Вводные'!B4="manual",'Вводные'!B5/100,IF(B8>0,B9/B8,1))-(IF(AND('Вводные'!B64="percent",'Вводные'!B67=1),'Вводные'!B65/100,0)+IF(AND('Вводные'!B70="percent",'Вводные'!B73=1),'Вводные'!B71/100,0)+IF('Вводные'!B61=1,'Вводные'!B55/100,0)+0)-IF('Вводные'!B6="revenue",'Вводные'!B7/100,0)),"") -> 1812820.5 | O57: При структуре затрат и продаж первого месяца, включая амортизацию и проценты.
A58: Первое покрытие вложений, месяц | N58: =IF(('Вводные'!B12)=0,0,IF(B50>=0,1,IF(C50>=0,2,IF(D50>=0,3,IF(E50>=0,4,IF(F50>=0,5,IF(G50>=0,6,IF(H50>=0,7,IF(I50>=0,8,IF(J50>=0,9,IF(K50>=0,10,IF(L50>=0,11,IF(M50>=0,12,"Не достигнуто"))))))))))))) -> 5
A59: Источник: введённые пользователем допущения. Начальные данные — пример, не рыночный прогноз.
A60: Выручка и затраты без НДС. Налоги и начисления вводятся пользователем. Без льгот и переноса убытков.
A61: Кредит и взнос до М1. Аннуитет с М1, без комиссий и досрочных погашений.
A62: Задержки оплаты: целые месяцы. Начальные дебиторская и кредиторская задолженности — 0.
A63: Оценка рекламной выручки не добавляется к обороту. Укажите эти продажи в плане выручки.
A64: Редактируйте значения на листе «Вводные». Формулы на листе «Модель» пересчитаются в Excel.

Sheet Вводные
A1: ВВОДНЫЕ / Изменённая
A2: Редактируйте колонку B. Суммы в KZT. Проценты задаются числом: 10 = 10%.
A3: Параметр | B3: Значение | C3: Пояснение
A4: Способ ввода выручки | B4: items | C4: items — товары; manual — ручной оборот
A5: Себестоимость ручного оборота, % | B5: 35
A6: База условного налога | B6: profit | C6: profit — прибыль; revenue — оборот; none — без налога
A7: Ставка налога, % | B7: 10
A8: Оплата клиентов через, мес. | B8: 0 | C8: Целые месяцы от 0 до 12
A9: Оплата себестоимости через, мес. | B9: 0 | C9: Целые месяцы от 0 до 12
A10: Деньги на начало | B10: 0
A11: Взнос собственника до М1 | B11: 3000000
A12: Вложения до М1 | B12: 3000000
A13: Амортизация начальных вложений, мес. (0 — нет) | B13: 36 | C13: 0 отключает амортизацию начальных вложений
A14: Кредит до М1 | B14: 0
A15: Годовая ставка кредита, % | B15: 18
A16: Срок кредита, мес. | B16: 24
A17: Множитель сценария | B17: 1 | C17: База: 1; осторожный: 0.8; оптимистичный: 1.2
A18: Ручной оборот · М1 | B18: 2550000
A19: Ручной оборот · М2 | B19: 2550000
A20: Ручной оборот · М3 | B20: 2550000
A21: Ручной оборот · М4 | B21: 2550000
A22: Ручной оборот · М5 | B22: 2550000
A23: Ручной оборот · М6 | B23: 2550000
A24: Ручной оборот · М7 | B24: 2550000
A25: Ручной оборот · М8 | B25: 2550000
A26: Ручной оборот · М9 | B26: 2550000
A27: Ручной оборот · М10 | B27: 2550000
A28: Ручной оборот · М11 | B28: 2550000
A29: Ручной оборот · М12 | B29: 2550000
A30: Основной продукт · Название | B30: Основной продукт
A31: Основной продукт · Количество в первый активный месяц | B31: 300
A32: Основной продукт · Цена | B32: 8500
A33: Основной продукт · Рост в месяц, % | B33: 4
A34: Основной продукт · Себестоимость, % выручки | B34: 35
A35: Основной продукт · С месяца | B35: 1 | C35: Номер периода: 1 — М1, …, 12 — М12
A36: Основной продукт · По месяц | B36: 12 | C36: Номер периода: 1 — М1, …, 12 — М12
A37: Менеджер · Название | B37: Менеджер
A38: Менеджер · Количество сотрудников | B38: 1
A39: Менеджер · Оклад одного / месяц | B39: 300000
A40: Менеджер · Бонус одного / месяц | B40: 0
A41: Менеджер · Начисления работодателя, % | B41: 15
A42: Менеджер · Рост в месяц, % | B42: 0
A43: Менеджер · С месяца | B43: 1 | C43: Номер периода: 1 — М1, …, 12 — М12
A44: Менеджер · По месяц | B44: 12 | C44: Номер периода: 1 — М1, …, 12 — М12
A45: Менеджер — копия · Название | B45: Менеджер — копия
A46: Менеджер — копия · Количество сотрудников | B46: 1
A47: Менеджер — копия · Оклад одного / месяц | B47: 300000
A48: Менеджер — копия · Бонус одного / месяц | B48: 0
A49: Менеджер — копия · Начисления работодателя, % | B49: 15
A50: Менеджер — копия · Рост в месяц, % | B50: 0
A51: Менеджер — копия · С месяца | B51: 1 | C51: Номер периода: 1 — М1, …, 12 — М12
A52: Менеджер — копия · По месяц | B52: 12 | C52: Номер периода: 1 — М1, …, 12 — М12
A53: Реклама · Название | B53: Реклама
A54: Реклама · Бюджет / месяц | B54: 120000
A55: Реклама · Дополнительно от выручки, % | B55: 0
A56: Реклама · Рост в месяц, % | B56: 0
A57: Реклама · Цена клика | B57: 150
A58: Реклама · Клики → заявки, % | B58: 10
A59: Реклама · Заявки → клиенты, % | B59: 20
A60: Реклама · Средний чек клиента | B60: 8500
A61: Реклама · С месяца | B61: 1 | C61: Номер периода: 1 — М1, …, 12 — М12
A62: Реклама · По месяц | B62: 12 | C62: Номер периода: 1 — М1, …, 12 — М12
A63: Аренда · Название | B63: Аренда
A64: Аренда · Способ расчёта | B64: fixed | C64: fixed — сумма; percent — % оборота; once — один раз
A65: Аренда · Сумма или ставка | B65: 250000
A66: Аренда · Рост в месяц, % | B66: 0
A67: Аренда · С месяца | B67: 1 | C67: Номер периода: 1 — М1, …, 12 — М12
A68: Аренда · По месяц | B68: 12 | C68: Номер периода: 1 — М1, …, 12 — М12
A69: Сервисы и связь · Название | B69: Сервисы и связь
A70: Сервисы и связь · Способ расчёта | B70: fixed | C70: fixed — сумма; percent — % оборота; once — один раз
A71: Сервисы и связь · Сумма или ставка | B71: 35000
A72: Сервисы и связь · Рост в месяц, % | B72: 0
A73: Сервисы и связь · С месяца | B73: 1 | C73: Номер периода: 1 — М1, …, 12 — М12
A74: Сервисы и связь · По месяц | B74: 12 | C74: Номер периода: 1 — М1, …, 12 — М12
